examples/__init__.py
flows/__init__.py
flows/distributions.py
flows/bijections/__init__.py
flows/bijections/bijections.py
flows/bijections/made.py
flows/bijections/neural_splines.py
tests/__init__.py
tests/test_bijections.py
tests/test_distributions.py
jax_flows-0.0.1.dist-info/LICENSE
jax_flows-0.0.1.dist-info/METADATA
jax_flows-0.0.1.dist-info/WHEEL
jax_flows-0.0.1.dist-info/top_level.txt
jax_flows-0.0.1.dist-info/RECORD
