Metadata-Version: 2.1
Name: jax-flows
Version: 0.0.1
Summary: Normalizing Flows for JAX
Home-page: http://github.com/ChrisWaites/jax-flows
Author: Chris Waites
Author-email: cwaites10@gmail.com
License: MIT
Platform: UNKNOWN
Classifier: Programming Language :: Python :: 3
Classifier: License :: OSI Approved :: MIT License
Classifier: Operating System :: OS Independent
Requires-Python: >=3.6.0
Requires-Dist: jax
Requires-Dist: jaxlib
Requires-Dist: numpy
Requires-Dist: scipy
Requires-Dist: sklearn
Provides-Extra: dev
Requires-Dist: pytest ; extra == 'dev'
Requires-Dist: pytest-xdist ; extra == 'dev'
Requires-Dist: black ; extra == 'dev'
Requires-Dist: isort ; extra == 'dev'
Requires-Dist: flake8 ; extra == 'dev'
Provides-Extra: docs
Requires-Dist: recommonmark ; extra == 'docs'
Requires-Dist: sphinx ; extra == 'docs'
Requires-Dist: sphinx-markdown-tables ; extra == 'docs'
Requires-Dist: sphinx-rtd-theme ; extra == 'docs'
Provides-Extra: quality
Requires-Dist: black ; extra == 'quality'
Requires-Dist: isort ; extra == 'quality'
Requires-Dist: flake8 ; extra == 'quality'
Provides-Extra: testing
Requires-Dist: pytest ; extra == 'testing'
Requires-Dist: pytest-xdist ; extra == 'testing'
